{
    "wallpaper": "/home/theo/.config/wpg/wallpapers/space.jpg",
    "alpha": "100",

    "special": {
        "background": "#000102",
        "foreground": "#9a9c9e",
        "cursor": "#9a9c9e"
    },
    "colors": {
        "color0": "#000102",
        "color1": "#0f233d",
        "color2": "#4d3e61",
        "color3": "#254f83",
        "color4": "#505c6c",
        "color5": "#3073b0",
        "color6": "#52b0db",
        "color7": "#9a9c9e",
        "color8": "#36393e",
        "color9": "#0f233d",
        "color10": "#4d3e61",
        "color11": "#254f83",
        "color12": "#505c6c",
        "color13": "#3073b0",
        "color14": "#52b0db",
        "color15": "#9a9c9e"
    }
}
